<annotation><filename>00012.jpg</filename><object> <name>gate</name><bndbox><xmin>114</xmin><ymin>189</ymin><xmax>224</xmax><ymax>299</ymax></bndbox><pose><north>4.92</north><east>-0.92</east><down>3.64149</down><yaw>0</yaw><pitch>0</pitch><roll>0</roll></pose><gate_corners><top_left>114,299</top_left><top_right>224,299</top_right><bottom_right>224,189</bottom_right><bottom_left>114,189</bottom_left><center>169,244</center></gate_corners></object><object> <name>gate</name><bndbox><xmin>218</xmin><ymin>201</ymin><xmax>257</xmax><ymax>240</ymax></bndbox><pose><north>13.66</north><east>1.96</east><down>3.64149</down><yaw>0</yaw><pitch>0</pitch><roll>0</roll></pose><gate_corners><top_left>218,240</top_left><top_right>257,240</top_right><bottom_right>257,201</bottom_right><bottom_left>218,201</bottom_left><center>237,221</center></gate_corners></object><object> <name>gate</name><bndbox><xmin>256</xmin><ymin>203</ymin><xmax>262</xmax><ymax>229</ymax></bndbox><pose><north>22.04</north><east>5.39</east><down>3.64149</down><yaw>0</yaw><pitch>0</pitch><roll>0</roll></pose><gate_corners><top_left>256,227</top_left><top_right>262,229</top_right><bottom_right>262,203</bottom_right><bottom_left>256,204</bottom_left><center>258,216</center></gate_corners></object><object> <name>gate</name><bndbox><xmin>398</xmin><ymin>199</ymin><xmax>448</xmax><ymax>249</ymax></bndbox><pose><north>10.9</north><east>11.3</east><down>3.64149</down><yaw>0</yaw><pitch>0</pitch><roll>0</roll></pose><gate_corners><top_left>398,249</top_left><top_right>448,249</top_right><bottom_right>448,199</bottom_right><bottom_left>398,199</bottom_left><center>423,224</center></gate_corners></object></annotation>