<annotation><filename>00101.jpg</filename><object> <name>gate</name><bndbox><xmin>258</xmin><ymin>182</ymin><xmax>342</xmax><ymax>265</ymax></bndbox><pose><north>6.54553</north><east>2.88624</east><down>4.35212</down><yaw>0</yaw><pitch>0</pitch><roll>0</roll></pose><gate_corners><top_left>259,265</top_left><top_right>342,265</top_right><bottom_right>340,182</bottom_right><bottom_left>258,182</bottom_left><center>299,223</center></gate_corners></object><object> <name>gate</name><bndbox><xmin>288</xmin><ymin>201</ymin><xmax>305</xmax><ymax>240</ymax></bndbox><pose><north>14.9255</north><east>6.31624</east><down>4.35212</down><yaw>0</yaw><pitch>0</pitch><roll>0</roll></pose><gate_corners><top_left>289,237</top_left><top_right>305,240</top_right><bottom_right>304,201</bottom_right><bottom_left>288,203</bottom_left><center>296,220</center></gate_corners></object></annotation>