<annotation><filename>00100.jpg</filename><object> <name>gate</name><bndbox><xmin>257</xmin><ymin>182</ymin><xmax>340</xmax><ymax>264</ymax></bndbox><pose><north>6.65267</north><east>2.8862</east><down>4.35206</down><yaw>0</yaw><pitch>0</pitch><roll>0</roll></pose><gate_corners><top_left>258,264</top_left><top_right>340,264</top_right><bottom_right>337,182</bottom_right><bottom_left>257,182</bottom_left><center>298,223</center></gate_corners></object><object> <name>gate</name><bndbox><xmin>288</xmin><ymin>201</ymin><xmax>304</xmax><ymax>240</ymax></bndbox><pose><north>15.0327</north><east>6.3162</east><down>4.35206</down><yaw>0</yaw><pitch>0</pitch><roll>0</roll></pose><gate_corners><top_left>288,237</top_left><top_right>304,240</top_right><bottom_right>303,201</bottom_right><bottom_left>288,203</bottom_left><center>295,220</center></gate_corners></object></annotation>