<annotation><filename>00819.jpg</filename><object> <name>gate</name><bndbox><xmin>118</xmin><ymin>180</ymin><xmax>182</xmax><ymax>246</ymax></bndbox><pose><north>2.46268</north><east>8.9143</east><down>1.67323</down><yaw>0</yaw><pitch>0</pitch><roll>0</roll></pose><gate_corners><top_left>182,243</top_left><top_right>122,246</top_right><bottom_right>118,184</bottom_right><bottom_left>179,180</bottom_left><center>150,213</center></gate_corners></object><object> <name>gate</name><bndbox><xmin>335</xmin><ymin>170</ymin><xmax>398</xmax><ymax>235</ymax></bndbox><pose><north>-6.86139</north><east>8.98967</east><down>1.67325</down><yaw>0</yaw><pitch>0</pitch><roll>0</roll></pose><gate_corners><top_left>398,232</top_left><top_right>338,235</top_right><bottom_right>335,173</bottom_right><bottom_left>395,170</bottom_left><center>366,202</center></gate_corners></object></annotation>