<annotation><filename>00900.jpg</filename><object> <name>gate</name><bndbox><xmin>-12</xmin><ymin>76</ymin><xmax>279</xmax><ymax>379</ymax></bndbox><pose><north>-0.686993</north><east>-1.94451</east><down>1.577</down><yaw>0</yaw><pitch>0</pitch><roll>0</roll></pose><gate_corners><top_left>-12,365</top_left><top_right>265,379</top_right><bottom_right>279,91</bottom_right><bottom_left>1,76</bottom_left><center>133,228</center></gate_corners></object><object> <name>gate</name><bndbox><xmin>234</xmin><ymin>186</ymin><xmax>290</xmax><ymax>244</ymax></bndbox><pose><north>2.66754</north><east>-10.1677</east><down>1.57702</down><yaw>0</yaw><pitch>0</pitch><roll>0</roll></pose><gate_corners><top_left>234,241</top_left><top_right>287,244</top_right><bottom_right>290,189</bottom_right><bottom_left>237,186</bottom_left><center>262,215</center></gate_corners></object><object> <name>gate</name><bndbox><xmin>69</xmin><ymin>179</ymin><xmax>122</xmax><ymax>234</ymax></bndbox><pose><north>-5.69192</north><east>-10.5934</east><down>1.57702</down><yaw>0</yaw><pitch>0</pitch><roll>0</roll></pose><gate_corners><top_left>69,231</top_left><top_right>120,234</top_right><bottom_right>122,181</bottom_right><bottom_left>72,179</bottom_left><center>96,206</center></gate_corners></object></annotation>